Metadata-Version: 2.1
Name: toiro
Version: 0.0.9
Summary: A comparison tool of Japanese tokenizers
Home-page: https://github.com/taishi-i/toiro
Author: Taishi Ikeda
Author-email: taishi.ikeda.0323@gmail.com
License: UNKNOWN
Download-URL: https://github.com/taishi-i/toiro/archive/0.0.9.tar.gz
Keywords: Japanese NLP
Platform: UNKNOWN
Classifier: License :: OSI Approved :: MIT License
Classifier: Natural Language :: Japanese
Classifier: Programming Language :: Python :: 3.6
Classifier: Programming Language :: Python :: 3.7
Classifier: Programming Language :: Python :: 3.8
Classifier: Programming Language :: Python :: 3.8
Classifier: Programming Language :: Python :: 3.9
Classifier: Programming Language :: Python :: 3.10
Classifier: Programming Language :: Python :: 3.11
Classifier: Operating System :: Unix
Classifier: Topic :: Text Processing :: Linguistic
Classifier: Topic :: Software Development :: Libraries :: Python Modules
Requires-Python: >=3.6.0
Requires-Dist: requests
Requires-Dist: tqdm
Requires-Dist: pandas
Requires-Dist: scikit-learn
Requires-Dist: py-cpuinfo
Requires-Dist: janome
Provides-Extra: all
Requires-Dist: nagisa ; extra == 'all'
Requires-Dist: sudachipy ; extra == 'all'
Requires-Dist: sudachidict-core ; extra == 'all'
Requires-Dist: mecab-python3 ; extra == 'all'
Requires-Dist: spacy ; extra == 'all'
Requires-Dist: ginza ; extra == 'all'
Requires-Dist: kytea ; extra == 'all'
Requires-Dist: pyknp ; extra == 'all'
Requires-Dist: sentencepiece ; extra == 'all'
Requires-Dist: fugashi ; extra == 'all'
Requires-Dist: ipadic ; extra == 'all'
Requires-Dist: unidic-lite ; extra == 'all'
Requires-Dist: tinysegmenter3 ; extra == 'all'
Requires-Dist: torch ; extra == 'all'
Requires-Dist: transformers ; extra == 'all'
Requires-Dist: catalyst ; extra == 'all'
Provides-Extra: all_classifiers
Requires-Dist: torch ; extra == 'all_classifiers'
Requires-Dist: transformers ; extra == 'all_classifiers'
Requires-Dist: catalyst ; extra == 'all_classifiers'
Provides-Extra: all_tokenizers
Requires-Dist: nagisa ; extra == 'all_tokenizers'
Requires-Dist: sudachipy ; extra == 'all_tokenizers'
Requires-Dist: sudachidict-core ; extra == 'all_tokenizers'
Requires-Dist: mecab-python3 ; extra == 'all_tokenizers'
Requires-Dist: spacy ; extra == 'all_tokenizers'
Requires-Dist: ginza ; extra == 'all_tokenizers'
Requires-Dist: kytea ; extra == 'all_tokenizers'
Requires-Dist: pyknp ; extra == 'all_tokenizers'
Requires-Dist: sentencepiece ; extra == 'all_tokenizers'
Requires-Dist: fugashi ; extra == 'all_tokenizers'
Requires-Dist: ipadic ; extra == 'all_tokenizers'
Requires-Dist: unidic-lite ; extra == 'all_tokenizers'
Requires-Dist: tinysegmenter3 ; extra == 'all_tokenizers'
